CryptX/__init__.py
CryptX-2020.3.1.dist-info/METADATA
CryptX-2020.3.1.dist-info/WHEEL
CryptX-2020.3.1.dist-info/entry_points.txt
CryptX-2020.3.1.dist-info/top_level.txt
CryptX-2020.3.1.dist-info/RECORD
