Metadata-Version: 2.1
Name: CryptX
Version: 2020.3.1
Summary: A Open-Source & Safe Message Encrypter & Decrypter
Home-page: https://github.com/TG-iDev/CryptX
Author: TechGeeks
Author-email: CryptX@tgeeks.cf
License: UNKNOWN
Platform: UNKNOWN
Classifier: Programming Language :: Python :: 3
Classifier: License :: OSI Approved :: MIT License
Classifier: Operating System :: OS Independent
Requires-Python: >=3.6
